odoo/addons/web_notify/README.rst
odoo/addons/web_notify/__init__.py
odoo/addons/web_notify/__manifest__.py
odoo/addons/web_notify/i18n/da.po
odoo/addons/web_notify/i18n/de.po
odoo/addons/web_notify/i18n/es.po
odoo/addons/web_notify/i18n/fr.po
odoo/addons/web_notify/i18n/hr.po
odoo/addons/web_notify/i18n/it.po
odoo/addons/web_notify/i18n/nl.po
odoo/addons/web_notify/i18n/nl_NL.po
odoo/addons/web_notify/i18n/pt_BR.po
odoo/addons/web_notify/i18n/web_notify.pot
odoo/addons/web_notify/i18n/zh_CN.po
odoo/addons/web_notify/models/__init__.py
odoo/addons/web_notify/models/res_users.py
odoo/addons/web_notify/readme/CONTRIBUTORS.rst
odoo/addons/web_notify/readme/DESCRIPTION.rst
odoo/addons/web_notify/readme/INSTALL.rst
odoo/addons/web_notify/readme/USAGE.rst
odoo/addons/web_notify/static/description/icon.png
odoo/addons/web_notify/static/description/index.html
odoo/addons/web_notify/static/description/notifications_screenshot.png
odoo/addons/web_notify/static/description/test_notifications_demo.png
odoo/addons/web_notify/static/src/js/web_client.js
odoo/addons/web_notify/static/src/js/widgets/notification.js
odoo/addons/web_notify/static/src/scss/webclient.scss
odoo/addons/web_notify/tests/__init__.py
odoo/addons/web_notify/tests/test_res_users.py
odoo/addons/web_notify/views/res_users_demo.xml
odoo/addons/web_notify/views/web_notify.xml
odoo14_addon_web_notify-14.0.1.1.0.dist-info/METADATA
odoo14_addon_web_notify-14.0.1.1.0.dist-info/WHEEL
odoo14_addon_web_notify-14.0.1.1.0.dist-info/top_level.txt
odoo14_addon_web_notify-14.0.1.1.0.dist-info/RECORD
