Metadata-Version: 2.1
Name: odoo14-addon-web-notify
Version: 14.0.1.1.0
Summary: Send notification messages to user
Home-page: https://github.com/OCA/web
Author: ACSONE SA/NV,AdaptiveCity,Odoo Community Association (OCA)
Author-email: support@odoo-community.org
License: AGPL-3
Platform: UNKNOWN
Classifier: Programming Language :: Python
Classifier: Framework :: Odoo
Classifier: Framework :: Odoo :: 14.0
Classifier: License :: OSI Approved :: GNU Affero General Public License v3
Classifier: Development Status :: 5 - Production/Stable
Requires-Python: >=3.6
Requires-Dist: odoo <14.1dev,>=14.0a
